opusxml/__init__.py
opusxml/cli/__init__.py
opusxml/cli/opusxml.py
opusxml/core/__init__.py
opusxml/core/api.py
opusxml/core/opus.py
opusxml/tools/__init__.py
opusxml/tools/fips_mapping.py
opusxml-0.0.0.dist-info/DESCRIPTION.rst
opusxml-0.0.0.dist-info/METADATA
opusxml-0.0.0.dist-info/RECORD
opusxml-0.0.0.dist-info/WHEEL
opusxml-0.0.0.dist-info/entry_points.txt
opusxml-0.0.0.dist-info/metadata.json
opusxml-0.0.0.dist-info/top_level.txt
