Metadata-Version: 2.0
Name: opusxml
Version: 0.0.0
Summary: Python library to read and convert OPUSXML files.
Home-page: http://github.com/mrahnis/opusxml
Author: Michael Rahnis
Author-email: michael.rahnis@fandm.edu
License: BSD
Keywords: cross-section,topography,survey
Platform: UNKNOWN
Classifier: Development Status :: 3 - Alpha
Classifier: License :: OSI Approved :: BSD License
Classifier: Programming Language :: Python
Classifier: Programming Language :: Python :: 2.7
Classifier: Programming Language :: Python :: 3
Classifier: Topic :: Scientific/Engineering :: GIS
Requires-Dist: click
Requires-Dist: fiona
Requires-Dist: lxml
Requires-Dist: pint
Requires-Dist: shapely
